align/__init__.py
align/calculate_alignment.py
align/datasets.py
align/prepare_transcripts.py
align/data/gutenberg.txt
align/data/CHILDES/CHILDES-license-human_readable.md
align/data/CHILDES/CHILDES-license-legal.md
align/data/CHILDES/time191-cond1.txt
align/data/CHILDES/time192-cond1.txt
align/data/CHILDES/time193-cond1.txt
align/data/CHILDES/time194-cond1.txt
align/data/CHILDES/time195-cond1.txt
align/data/CHILDES/time196-cond1.txt
align/data/CHILDES/time197-cond1.txt
align/data/CHILDES/time198-cond1.txt
align/data/CHILDES/time199-cond1.txt
align/data/CHILDES/time200-cond1.txt
align/data/CHILDES/time201-cond1.txt
align/data/CHILDES/time202-cond1.txt
align/data/CHILDES/time203-cond1.txt
align/data/CHILDES/time204-cond1.txt
align/data/CHILDES/time205-cond1.txt
align/data/CHILDES/time206-cond1.txt
align/data/CHILDES/time207-cond1.txt
align/data/CHILDES/time208-cond1.txt
align/data/CHILDES/time209-cond1.txt
align/data/CHILDES/time210-cond1.txt
align-0.1.1.dist-info/LICENSE
align-0.1.1.dist-info/METADATA
align-0.1.1.dist-info/WHEEL
align-0.1.1.dist-info/top_level.txt
align-0.1.1.dist-info/RECORD
