Metadata-Version: 2.1
Name: align
Version: 0.1.1
Summary: Analyzing Linguistic Interaction with Generalizable techNiques. Read the latest ALIGN tutorials.
Author-email: Nicholas Duran <nickduran101@gmail.com>, Alexandra Paxton <paxton.alexandra@gmail.com>, Riccardo Fusaroli <fusaroli@gmail.com>
License: LICENSE
Project-URL: Homepage, https://github.com/nickduran/align-linguistic-alignment
Keywords: linguistic-analysis,linguistic-alignment,corpus-tools,conversation-analysis,ngram-analysis,text-analysis,nltk,word2vec,notebooks
Classifier: License :: OSI Approved :: MIT License
Classifier: Programming Language :: Python :: 3
Classifier: Framework :: Jupyter
Classifier: Topic :: Text Processing :: Linguistic
Requires-Python: >=3.10
License-File: LICENSE
Requires-Dist: numpy (>=1.22.3)
Requires-Dist: scipy (>=1.7.3)
Requires-Dist: gensim (>=4.1.2)
Requires-Dist: pandas (>=1.4.2)
Requires-Dist: nltk (>=3.7)
Requires-Dist: ipython (>=8.3.0)
